robovac/LocalServerInfo_pb2.py
robovac/__init__.py
robovac/robovac.py
robovac-0.0.8.dist-info/LICENSE
robovac-0.0.8.dist-info/METADATA
robovac-0.0.8.dist-info/WHEEL
robovac-0.0.8.dist-info/top_level.txt
robovac-0.0.8.dist-info/RECORD
