Metadata-Version: 2.1
Name: robovac
Version: 0.0.8
Summary: Python API for communicating with Eufy RoboVac 11c devices
Home-page: https://github.com/bnmcg/pyrobovac
Author: BnMcG
Author-email: ben@bmagee.com
License: UNKNOWN
Platform: UNKNOWN
Classifier: Programming Language :: Python :: 3
Classifier: License :: OSI Approved :: Apache Software License
Classifier: Operating System :: OS Independent
Requires-Dist: protobuf
Requires-Dist: pycryptodome
Requires-Dist: six
Requires-Dist: requests
